<?xml version="1.0" encoding="utf-8"?>
<publishData>
  <publishProfile publishUrl="E:\My Project\MVC Project\web\YTech.Ltr.Web" deleteExistingFiles="False" ftpAnonymousLogin="False" ftpPassiveMode="True" msdeploySite="" msdeploySiteID="" msdeployRemoteSitePhysicalPath="" msdeployAllowUntrustedCertificate="False" msdeploySkipExtraFilesOnServer="True" msdeployMarkAsApp="False" profileName="localhost/Ltr" publishMethod="FileSystem" replaceMatchingFiles="True" userName="" savePWD="False" userPWD="" SelectedForPublish="True">
    <file relUrl="Content/img/go-up-off.gif" publishTime="04/14/2011 10:45:47" />
    <file relUrl="Scripts/MicrosoftAjax.js" publishTime="04/13/2011 16:01:03" />
    <file relUrl="bin/Microsoft.ReportViewer.ProcessingObjectModel.dll" publishTime="04/15/2011 06:51:07" />
    <file relUrl="Content/img/toggle-dn.gif" publishTime="04/14/2011 10:45:47" />
    <file relUrl="Views/Utility/UserAccount/ChangePasswordSuccess.aspx" publishTime="04/14/2011 10:45:47" />
    <file relUrl="bin/SharpArch.pdb" publishTime="04/13/2011 16:01:03" />
    <file relUrl="bin/PagedList.pdb" publishTime="04/12/2011 10:28:43" />
    <file relUrl="Content/img/resizable-n.gif" publishTime="04/14/2011 10:45:47" />
    <file relUrl="bin/MvcMembership.pdb" publishTime="04/12/2011 10:28:42" />
    <file relUrl="bin/sqlceca35.dll" publishTime="04/22/2011 05:20:10" />
    <file relUrl="Views/Master/Agent/Index.aspx" publishTime="04/22/2011 04:28:41" />
    <file relUrl="Views/Shared/DebugFormSubmission.ascx" publishTime="04/13/2011 16:01:03" />
    <file relUrl="ReportViewer.aspx" publishTime="04/16/2011 22:24:24" />
    <file relUrl="Content/img/toggle-rt.gif" publishTime="04/14/2011 10:45:47" />
    <file relUrl="Views/Web.config" publishTime="04/13/2011 16:01:03" />
    <file relUrl="Content/css/start/images/ui-icons_f5e175_256x240.png" publishTime="04/14/2011 10:45:47" />
    <file relUrl="Views/Utility/UserAccount/LogOn.aspx" publishTime="04/14/2011 10:45:47" />
    <file relUrl="bin/YTech.Ltr.Web.dll" publishTime="04/22/2011 05:42:11" />
    <file relUrl="Content/css/start/images/ui-icons_0078ae_256x240.png" publishTime="04/14/2011 10:45:47" />
    <file relUrl="bin/NHibernate.ByteCode.Castle.dll" publishTime="04/13/2011 16:00:51" />
    <file relUrl="bin/Castle.Core.dll" publishTime="04/13/2011 16:00:46" />
    <file relUrl="bin/System.Web.Abstractions.dll" publishTime="04/13/2011 16:00:55" />
    <file relUrl="Content/img/go-lt-off.gif" publishTime="04/14/2011 10:45:47" />
    <file relUrl="Content/ui.jqgrid.css" publishTime="04/14/2011 10:45:47" />
    <file relUrl="Content/img/pin-up-off.gif" publishTime="04/14/2011 10:45:47" />
    <file relUrl="bin/FluentNHibernate.dll" publishTime="04/13/2011 16:00:47" />
    <file relUrl="Content/css/start/images/ui-bg_flat_75_aaaaaa_40x100.png" publishTime="04/14/2011 10:45:47" />
    <file relUrl="Scripts/jquery-ui.min.js" publishTime="04/14/2011 10:45:47" />
    <file relUrl="Content/css/start/jquery-ui.css" publishTime="04/14/2011 10:45:47" />
    <file relUrl="Content/css/start/images/ui-icons_e0fdff_256x240.png" publishTime="04/14/2011 10:45:47" />
    <file relUrl="Views/Utility/UserAccount/Register.aspx" publishTime="04/14/2011 10:45:47" />
    <file relUrl="bin/NHibernate.Validator.dll" publishTime="04/13/2011 16:00:52" />
    <file relUrl="Content/img/pin-up-on.gif" publishTime="04/14/2011 10:45:47" />
    <file relUrl="Content/css/start/images/ui-bg_glass_45_0078ae_1x400.png" publishTime="04/14/2011 10:45:47" />
    <file relUrl="Views/Transaction/Report/Report.aspx" publishTime="04/15/2011 06:51:07" />
    <file relUrl="Views/Transaction/Report/RptRecapSalesByAgent.rdlc" publishTime="04/21/2011 16:40:15" />
    <file relUrl="bin/sqlceoledb35.dll" publishTime="04/22/2011 05:20:10" />
    <file relUrl="bin/Inflector.Net.dll" publishTime="04/13/2011 16:00:49" />
    <file relUrl="Content/img/80ade5_40x100_textures_04_highlight_hard_100.png" publishTime="04/14/2011 10:45:47" />
    <file relUrl="Content/css/start/images/ui-bg_gloss-wave_45_e14f1c_500x100.png" publishTime="04/14/2011 10:45:47" />
    <file relUrl="bin/DB_LTR.sdf" publishTime="04/22/2011 05:13:04" />
    <file relUrl="Scripts/jquery.layout.min.js" publishTime="04/14/2011 10:45:47" />
    <file relUrl="bin/Newtonsoft.Json.xml" publishTime="04/13/2011 16:01:03" />
    <file relUrl="bin/Remotion.Data.Linq.dll" publishTime="04/13/2011 16:00:53" />
    <file relUrl="Views/Shared/MyMaster.master" publishTime="04/14/2011 10:45:47" />
    <file relUrl="Content/img/toggle-up.gif" publishTime="04/14/2011 10:45:47" />
    <file relUrl="bin/sqlcecompact35.dll" publishTime="04/22/2011 05:20:10" />
    <file relUrl="Views/Transaction/Report/RptRecapSalesByGame.rdlc" publishTime="04/21/2011 16:40:15" />
    <file relUrl="bin/Microsoft.Practices.ServiceLocation.dll" publishTime="04/13/2011 16:00:48" />
    <file relUrl="bin/FluentNHibernate.xml" publishTime="04/13/2011 16:01:03" />
    <file relUrl="Scripts/MicrosoftMvcAjax.debug.js" publishTime="04/14/2011 10:45:47" />
    <file relUrl="Views/Shared/LogOnUserControl.ascx" publishTime="04/14/2011 10:45:47" />
    <file relUrl="Content/css/start/images/ui-bg_inset-hard_100_fcfdfd_1x100.png" publishTime="04/14/2011 10:45:47" />
    <file relUrl="Views/Transaction/Report/RptDetailSales.rdlc" publishTime="04/21/2011 16:40:15" />
    <file relUrl="Scripts/MicrosoftMvcAjax.js" publishTime="04/13/2011 16:01:03" />
    <file relUrl="bin/YTech.Ltr.Data.dll" publishTime="04/22/2011 05:10:29" />
    <file relUrl="bin/Newtonsoft.Json.dll" publishTime="04/13/2011 16:00:50" />
    <file relUrl="Content/img/d6d6d6_40x100_textures_02_glass_80.png" publishTime="04/14/2011 10:45:47" />
    <file relUrl="Content/Images/sharp_arch_small.gif" publishTime="04/13/2011 16:00:43" />
    <file relUrl="bin/Castle.Windsor.dll" publishTime="04/13/2011 16:00:45" />
    <file relUrl="bin/PagedList.xml" publishTime="04/14/2011 10:45:47" />
    <file relUrl="Views/Shared/Js.ascx" publishTime="04/14/2011 10:45:47" />
    <file relUrl="Scripts/jquery-1.4.4.min.js" publishTime="04/14/2011 10:45:47" />
    <file relUrl="Views/Transaction/Result/Result.aspx" publishTime="04/16/2011 22:24:24" />
    <file relUrl="Global.asax" publishTime="04/13/2011 16:01:03" />
    <file relUrl="bin/SharpArch.dll" publishTime="04/13/2011 16:00:54" />
    <file relUrl="bin/Castle.Windsor.xml" publishTime="04/13/2011 16:01:03" />
    <file relUrl="bin/log4net.dll" publishTime="04/13/2011 16:00:50" />
    <file relUrl="Scripts/MicrosoftMvcValidation.js" publishTime="04/14/2011 10:45:47" />
    <file relUrl="bin/log4net.xml" publishTime="04/13/2011 16:01:03" />
    <file relUrl="Web.config" publishTime="04/22/2011 05:23:21" />
    <file relUrl="Content/Images/window16.gif" publishTime="04/14/2011 10:45:47" />
    <file relUrl="bin/MvcContrib.FluentHtml.dll" publishTime="04/13/2011 16:00:50" />
    <file relUrl="bin/System.Data.SqlServerCe.dll" publishTime="02/12/2010 04:18:28" />
    <file relUrl="bin/YTech.Ltr.Web.pdb" publishTime="04/22/2011 05:42:11" />
    <file relUrl="bin/System.Web.Mvc.dll" publishTime="04/13/2011 16:00:55" />
    <file relUrl="Content/css/layout-default-latest.css" publishTime="04/14/2011 10:45:47" />
    <file relUrl="Content/css/complex.css" publishTime="04/14/2011 10:45:47" />
    <file relUrl="bin/System.Web.Mvc.xml" publishTime="04/13/2011 16:01:03" />
    <file relUrl="Scripts/jquery.jqGrid.min.js" publishTime="04/14/2011 10:45:47" />
    <file relUrl="Scripts/jquery.tooltip.js" publishTime="04/14/2011 10:45:47" />
    <file relUrl="bin/MvcContrib.xml" publishTime="04/13/2011 16:01:03" />
    <file relUrl="bin/nunit.framework.xml" publishTime="04/13/2011 16:01:03" />
    <file relUrl="bin/YTech.Ltr.Enums.dll" publishTime="04/22/2011 04:54:02" />
    <file relUrl="bin/sqlcese35.dll" publishTime="04/22/2011 05:20:10" />
    <file relUrl="Views/Transaction/Report/RptRecapWinSales.rdlc" publishTime="04/21/2011 16:40:15" />
    <file relUrl="bin/YTech.Ltr.ApplicationServices.dll" publishTime="04/22/2011 04:54:03" />
    <file relUrl="bin/MbUnit.dll" publishTime="04/13/2011 16:00:47" />
    <file relUrl="Content/img/D1E6FC_40x100_textures_10_dots_medium_90.png" publishTime="04/14/2011 10:45:47" />
    <file relUrl="bin/MvcContrib.FluentHtml.xml" publishTime="04/13/2011 16:01:03" />
    <file relUrl="Scripts/jquery.mousewheel-3.0.4.js" publishTime="04/14/2011 10:45:47" />
    <file relUrl="bin/NHibernate.Validator.xml" publishTime="04/13/2011 16:01:03" />
    <file relUrl="bin/YTech.Ltr.Core.dll" publishTime="04/22/2011 04:54:02" />
    <file relUrl="bin/PagedList.dll" publishTime="04/14/2011 10:45:47" />
    <file relUrl="Scripts/jquery.maskedinput-1.2.2.min.js" publishTime="04/14/2011 10:45:47" />
    <file relUrl="Content/img/go-dn-on.gif" publishTime="04/14/2011 10:45:47" />
    <file relUrl="Scripts/NumberFormat.js" publishTime="04/14/2011 10:45:47" />
    <file relUrl="Default.aspx" publishTime="04/13/2011 16:01:03" />
    <file relUrl="Content/Images/sharp_arch.jpg" publishTime="04/13/2011 16:00:43" />
    <file relUrl="Content/css/start/images/ui-bg_glass_75_79c9ec_1x400.png" publishTime="04/14/2011 10:45:47" />
    <file relUrl="bin/MvcMembership.dll" publishTime="04/14/2011 10:45:47" />
    <file relUrl="Content/css/start/images/ui-icons_fcd113_256x240.png" publishTime="04/14/2011 10:45:47" />
    <file relUrl="Content/img/go-rt-on.gif" publishTime="04/14/2011 10:45:47" />
    <file relUrl="bin/YTech.Ltr.Web.Controllers.dll" publishTime="04/22/2011 05:10:30" />
    <file relUrl="bin/NHibernate.xml" publishTime="04/13/2011 16:01:03" />
    <file relUrl="Content/css/start/images/ui-bg_glass_55_f8da4e_1x400.png" publishTime="04/14/2011 10:45:47" />
    <file relUrl="Scripts/jquery-1.4.2.min.js" publishTime="04/13/2011 16:01:03" />
    <file relUrl="Content/img/go-rt-off.gif" publishTime="04/14/2011 10:45:47" />
    <file relUrl="Views/Shared/UIMaster.Master" publishTime="04/22/2011 03:56:12" />
    <file relUrl="bin/Microsoft.ReportViewer.Common.dll" publishTime="03/18/2010 22:27:40" />
    <file relUrl="Content/img/go-lt-on.gif" publishTime="04/14/2011 10:45:47" />
    <file relUrl="Content/css/start/images/ui-bg_gloss-wave_75_2191c0_500x100.png" publishTime="04/14/2011 10:45:47" />
    <file relUrl="bin/sqlceqp35.dll" publishTime="04/22/2011 05:20:10" />
    <file relUrl="Views/Transaction/Report/ReportParamForm.ascx" publishTime="04/20/2011 01:29:04" />
    <file relUrl="bin/YTech.Ltr.Data.pdb" publishTime="04/22/2011 05:10:29" />
    <file relUrl="bin/Microsoft.ReportViewer.WebForms.xml" publishTime="03/03/2010 21:11:32" />
    <file relUrl="bin/Antlr3.Runtime.dll" publishTime="04/13/2011 16:00:45" />
    <file relUrl="bin/NHibernate.ByteCode.Castle.xml" publishTime="04/13/2011 16:01:03" />
    <file relUrl="bin/NHibernate.config" publishTime="04/22/2011 05:42:01" />
    <file relUrl="Views/Transaction/Sales/Sales.aspx" publishTime="04/22/2011 04:45:09" />
    <file relUrl="Scripts/jquery.layout.state.js" publishTime="04/14/2011 10:45:47" />
    <file relUrl="Content/img/resizable-w.gif" publishTime="04/14/2011 10:45:47" />
    <file relUrl="Content/img/eeeeee_40x100_textures_02_glass_90.png" publishTime="04/14/2011 10:45:47" />
    <file relUrl="bin/sqlceme35.dll" publishTime="04/22/2011 05:20:10" />
    <file relUrl="Content/img/pin-dn-on.gif" publishTime="04/14/2011 10:45:47" />
    <file relUrl="DB_LTR.sdf" publishTime="04/22/2011 05:13:04" />
    <file relUrl="bin/nunit.framework.dll" publishTime="04/13/2011 16:00:53" />
    <file relUrl="bin/Castle.Core.xml" publishTime="04/13/2011 16:01:03" />
    <file relUrl="Scripts/jquery-1.4.1-vsdoc.js" publishTime="04/14/2011 10:45:47" />
    <file relUrl="bin/CommonServiceLocator.WindsorAdapter.dll" publishTime="04/13/2011 16:00:46" />
    <file relUrl="Content/img/resizable-s.gif" publishTime="04/14/2011 10:45:47" />
    <file relUrl="Views/Master/Agent/Commission.aspx" publishTime="04/22/2011 04:33:30" />
    <file relUrl="Scripts/grid.locale-en.js" publishTime="04/14/2011 10:45:47" />
    <file relUrl="Scripts/date.format.js" publishTime="04/14/2011 10:45:47" />
    <file relUrl="Content/img/pin-dn-off.gif" publishTime="04/14/2011 10:45:47" />
    <file relUrl="Scripts/autoNumeric-1.6.2.js" publishTime="04/14/2011 10:45:47" />
    <file relUrl="bin/NHibernate.dll" publishTime="04/13/2011 16:00:52" />
    <file relUrl="Content/Site.css" publishTime="04/13/2011 16:01:03" />
    <file relUrl="Views/Shared/Menu.ascx" publishTime="04/22/2011 03:26:39" />
    <file relUrl="Views/Shared/Error.aspx" publishTime="04/17/2011 01:41:51" />
    <file relUrl="Views/Home/Index.aspx" publishTime="04/14/2011 10:45:47" />
    <file relUrl="Scripts/jquery.colorbox-min.js" publishTime="04/14/2011 10:45:47" />
    <file relUrl="Scripts/MicrosoftAjax.debug.js" publishTime="04/14/2011 10:45:47" />
    <file relUrl="bin/YTech.Ltr.ApplicationServices.pdb" publishTime="04/22/2011 04:54:03" />
    <file relUrl="bin/Iesi.Collections.xml" publishTime="04/13/2011 16:01:03" />
    <file relUrl="bin/Microsoft.ReportViewer.WebForms.dll" publishTime="03/18/2010 22:27:40" />
    <file relUrl="Views/Shared/MasterPopup.master" publishTime="04/20/2011 02:14:53" />
    <file relUrl="Scripts/default.js" publishTime="04/14/2011 10:45:47" />
    <file relUrl="Content/css/start/images/ui-bg_gloss-wave_50_6eac2c_500x100.png" publishTime="04/14/2011 10:45:47" />
    <file relUrl="Content/img/toggle-lt.gif" publishTime="04/14/2011 10:45:47" />
    <file relUrl="Views/Shared/Status.ascx" publishTime="04/14/2011 10:45:47" />
    <file relUrl="Content/img/go-up-on.gif" publishTime="04/14/2011 10:45:47" />
    <file relUrl="bin/sqlceer35EN.dll" publishTime="04/22/2011 05:20:10" />
    <file relUrl="bin/System.Web.Routing.dll" publishTime="04/13/2011 16:00:56" />
    <file relUrl="Content/css/master.css" publishTime="04/14/2011 10:45:47" />
    <file relUrl="Content/css/start/images/ui-icons_056b93_256x240.png" publishTime="04/14/2011 10:45:47" />
    <file relUrl="Content/css/start/images/ui-bg_flat_55_999999_40x100.png" publishTime="04/14/2011 10:45:47" />
    <file relUrl="bin/YTech.Ltr.Web.Controllers.pdb" publishTime="04/22/2011 05:10:30" />
    <file relUrl="bin/Gallio.dll" publishTime="04/13/2011 16:00:47" />
    <file relUrl="Scripts/jquery-1.4.2.js" publishTime="04/13/2011 16:01:03" />
    <file relUrl="bin/YTech.Ltr.Enums.pdb" publishTime="04/22/2011 04:54:02" />
    <file relUrl="Content/css/start/images/ui-icons_d8e7f3_256x240.png" publishTime="04/14/2011 10:45:47" />
    <file relUrl="NHibernate.config" publishTime="04/22/2011 05:42:01" />
    <file relUrl="Scripts/jquery.validate.min.js" publishTime="04/14/2011 10:45:47" />
    <file relUrl="Views/Shared/ParentMaster.Master" publishTime="04/14/2011 10:45:47" />
    <file relUrl="Content/img/go-dn-off.gif" publishTime="04/14/2011 10:45:47" />
    <file relUrl="Views/Utility/UserAccount/ChangePassword.aspx" publishTime="04/14/2011 10:45:47" />
    <file relUrl="Content/img/resizable-e.gif" publishTime="04/14/2011 10:45:47" />
    <file relUrl="bin/Iesi.Collections.dll" publishTime="04/13/2011 16:00:48" />
    <file relUrl="bin/MvcContrib.dll" publishTime="04/13/2011 16:00:49" />
    <file relUrl="bin/Microsoft.Web.Mvc.dll" publishTime="04/13/2011 16:00:49" />
    <file relUrl="Scripts/complex.js" publishTime="04/14/2011 10:45:47" />
    <file relUrl="Views/Shared/Site.Master" publishTime="04/13/2011 16:01:03" />
    <file relUrl="bin/YTech.Ltr.Core.pdb" publishTime="04/22/2011 04:54:02" />
    <file relUrl="Content/css/start/images/ui-icons_f7a50d_256x240.png" publishTime="04/14/2011 10:45:47" />
  </publishProfile>
</publishData>